<!--L
  Copyright Oracle Inc

  Distributed under the OSI-approved BSD 3-Clause License.
  See http://ncip.github.com/cadsr-cgmdr-nci-uk/LICENSE.txt for details.
L-->

<collection xmlns="http://exist.sourceforge.net/NS/exist" name="/db/mdr/selenium/core/scripts" owner="admin" group="dba" mode="755" created="2008-06-25T14:57:39+01:00" version="1">
    <resource type="BinaryResource" name="find_matching_child.js" owner="admin" group="dba" mode="755" created="2008-06-25T14:57:39+01:00" modified="2008-06-25T14:57:39+01:00" filename="find_matching_child.js" mimetype="application/x-javascript"/>
    <resource type="BinaryResource" name="htmlutils.js" owner="admin" group="dba" mode="755" created="2008-06-25T14:57:39+01:00" modified="2008-06-25T14:57:39+01:00" filename="htmlutils.js" mimetype="application/x-javascript"/>
    <resource type="BinaryResource" name="injection.html" owner="admin" group="dba" mode="755" created="2008-06-25T14:57:39+01:00" modified="2008-06-25T14:57:39+01:00" filename="injection.html" mimetype="text/html"/>
    <resource type="BinaryResource" name="js2html.js" owner="admin" group="dba" mode="755" created="2008-06-25T14:57:39+01:00" modified="2008-06-25T14:57:39+01:00" filename="js2html.js" mimetype="application/x-javascript"/>
    <resource type="BinaryResource" name="narcissus-defs.js" owner="admin" group="dba" mode="755" created="2008-06-25T14:57:39+01:00" modified="2008-06-25T14:57:39+01:00" filename="narcissus-defs.js" mimetype="application/x-javascript"/>
    <resource type="BinaryResource" name="narcissus-exec.js" owner="admin" group="dba" mode="755" created="2008-06-25T14:57:39+01:00" modified="2008-06-25T14:57:39+01:00" filename="narcissus-exec.js" mimetype="application/x-javascript"/>
    <resource type="BinaryResource" name="narcissus-parse.js" owner="admin" group="dba" mode="755" created="2008-06-25T14:57:39+01:00" modified="2008-06-25T14:57:39+01:00" filename="narcissus-parse.js" mimetype="application/x-javascript"/>
    <resource type="BinaryResource" name="se2html.js" owner="admin" group="dba" mode="755" created="2008-06-25T14:57:39+01:00" modified="2008-06-25T14:57:39+01:00" filename="se2html.js" mimetype="application/x-javascript"/>
    <resource type="BinaryResource" name="selenium-api.js" owner="admin" group="dba" mode="755" created="2008-06-25T14:57:39+01:00" modified="2008-06-25T14:57:39+01:00" filename="selenium-api.js" mimetype="application/x-javascript"/>
    <resource type="BinaryResource" name="selenium-browserbot.js" owner="admin" group="dba" mode="755" created="2008-06-25T14:57:39+01:00" modified="2008-06-25T14:57:39+01:00" filename="selenium-browserbot.js" mimetype="application/x-javascript"/>
    <resource type="BinaryResource" name="selenium-browserdetect.js" owner="admin" group="dba" mode="755" created="2008-06-25T14:57:39+01:00" modified="2008-06-25T14:57:39+01:00" filename="selenium-browserdetect.js" mimetype="application/x-javascript"/>
    <resource type="BinaryResource" name="selenium-commandhandlers.js" owner="admin" group="dba" mode="755" created="2008-06-25T14:57:39+01:00" modified="2008-06-25T14:57:39+01:00" filename="selenium-commandhandlers.js" mimetype="application/x-javascript"/>
    <resource type="BinaryResource" name="selenium-executionloop.js" owner="admin" group="dba" mode="755" created="2008-06-25T14:57:39+01:00" modified="2008-06-25T14:57:39+01:00" filename="selenium-executionloop.js" mimetype="application/x-javascript"/>
    <resource type="BinaryResource" name="selenium-logging.js" owner="admin" group="dba" mode="755" created="2008-06-25T14:57:40+01:00" modified="2008-06-25T14:57:40+01:00" filename="selenium-logging.js" mimetype="application/x-javascript"/>
    <resource type="BinaryResource" name="selenium-remoterunner.js" owner="admin" group="dba" mode="755" created="2008-06-25T14:57:40+01:00" modified="2008-06-25T14:57:40+01:00" filename="selenium-remoterunner.js" mimetype="application/x-javascript"/>
    <resource type="BinaryResource" name="selenium-testrunner.js" owner="admin" group="dba" mode="755" created="2008-06-25T14:57:40+01:00" modified="2008-06-25T14:57:40+01:00" filename="selenium-testrunner.js" mimetype="application/x-javascript"/>
    <resource type="BinaryResource" name="selenium-version.js" owner="admin" group="dba" mode="755" created="2008-06-25T14:57:40+01:00" modified="2008-06-25T14:57:40+01:00" filename="selenium-version.js" mimetype="application/x-javascript"/>
    <resource type="BinaryResource" name="user-extensions.js" owner="admin" group="dba" mode="755" created="2008-06-25T14:57:40+01:00" modified="2008-06-25T14:57:40+01:00" filename="user-extensions.js" mimetype="application/x-javascript"/>
    <resource type="BinaryResource" name="user-extensions.js.sample" owner="admin" group="dba" mode="755" created="2008-06-25T14:57:40+01:00" modified="2008-06-25T14:57:40+01:00" filename="user-extensions.js.sample" mimetype="application/octet-stream"/>
    <resource type="BinaryResource" name="xmlextras.js" owner="admin" group="dba" mode="755" created="2008-06-25T14:57:40+01:00" modified="2008-06-25T14:57:40+01:00" filename="xmlextras.js" mimetype="application/x-javascript"/>
</collection>