<collection xmlns="http://exist.sourceforge.net/NS/exist" name="/db/mdr/model/EARoot/EA4/EA3/EA2" owner="admin" group="dba" mode="755" created="2008-07-02T11:32:52+01:00" version="1">
    <resource type="BinaryResource" name="EA238.htm" owner="admin" group="dba" mode="755" created="2008-07-02T11:32:52+01:00" modified="2008-07-02T11:32:52+01:00" filename="EA238.htm" mimetype="text/html"/>
    <resource type="BinaryResource" name="EA239.png" owner="admin" group="dba" mode="755" created="2008-07-02T11:32:52+01:00" modified="2008-07-02T11:32:52+01:00" filename="EA239.png" mimetype="image/png"/>
    <resource type="BinaryResource" name="EA240.htm" owner="admin" group="dba" mode="755" created="2008-07-02T11:32:52+01:00" modified="2008-07-02T11:32:52+01:00" filename="EA240.htm" mimetype="text/html"/>
    <resource type="BinaryResource" name="EA241.htm" owner="admin" group="dba" mode="755" created="2008-07-02T11:32:52+01:00" modified="2008-07-02T11:32:52+01:00" filename="EA241.htm" mimetype="text/html"/>
    <resource type="BinaryResource" name="EA242.htm" owner="admin" group="dba" mode="755" created="2008-07-02T11:32:52+01:00" modified="2008-07-02T11:32:52+01:00" filename="EA242.htm" mimetype="text/html"/>
    <resource type="BinaryResource" name="EA243.htm" owner="admin" group="dba" mode="755" created="2008-07-02T11:32:53+01:00" modified="2008-07-02T11:32:53+01:00" filename="EA243.htm" mimetype="text/html"/>
    <resource type="BinaryResource" name="EA244.htm" owner="admin" group="dba" mode="755" created="2008-07-02T11:32:53+01:00" modified="2008-07-02T11:32:53+01:00" filename="EA244.htm" mimetype="text/html"/>
    <resource type="BinaryResource" name="EA245.htm" owner="admin" group="dba" mode="755" created="2008-07-02T11:32:53+01:00" modified="2008-07-02T11:32:53+01:00" filename="EA245.htm" mimetype="text/html"/>
    <resource type="BinaryResource" name="EA246.htm" owner="admin" group="dba" mode="755" created="2008-07-02T11:32:53+01:00" modified="2008-07-02T11:32:53+01:00" filename="EA246.htm" mimetype="text/html"/>
    <resource type="BinaryResource" name="EA247.htm" owner="admin" group="dba" mode="755" created="2008-07-02T11:32:53+01:00" modified="2008-07-02T11:32:53+01:00" filename="EA247.htm" mimetype="text/html"/>
    <resource type="BinaryResource" name="EA248.htm" owner="admin" group="dba" mode="755" created="2008-07-02T11:32:53+01:00" modified="2008-07-02T11:32:53+01:00" filename="EA248.htm" mimetype="text/html"/>
    <resource type="BinaryResource" name="EA249.htm" owner="admin" group="dba" mode="755" created="2008-07-02T11:32:53+01:00" modified="2008-07-02T11:32:53+01:00" filename="EA249.htm" mimetype="text/html"/>
    <resource type="BinaryResource" name="EA250.htm" owner="admin" group="dba" mode="755" created="2008-07-02T11:32:53+01:00" modified="2008-07-02T11:32:53+01:00" filename="EA250.htm" mimetype="text/html"/>
    <resource type="BinaryResource" name="EA251.htm" owner="admin" group="dba" mode="755" created="2008-07-02T11:32:53+01:00" modified="2008-07-02T11:32:53+01:00" filename="EA251.htm" mimetype="text/html"/>
    <resource type="BinaryResource" name="contents.htm" owner="admin" group="dba" mode="755" created="2008-07-02T11:32:52+01:00" modified="2008-07-02T11:32:52+01:00" filename="contents.htm" mimetype="text/html"/>
</collection>